ucefcdownloader/__init__.py
ucefcdownloader/core.py
ucefcdownloader/utils.py
ucefcdownloader/__metadata__/DISCLIAIMER.md
ucefcdownloader/__metadata__/LICENSE
ucefcdownloader/__metadata__/README.md
ucefcdownloader/__metadata__/__init__.py
ucefcdownloader/__metadata__/requirements.txt
ucefcdownloader-0.2.0.dist-info/METADATA
ucefcdownloader-0.2.0.dist-info/WHEEL
ucefcdownloader-0.2.0.dist-info/top_level.txt
ucefcdownloader-0.2.0.dist-info/RECORD
