Metadata-Version: 2.1
Name: ucefcdownloader
Version: 0.2.0
Summary: ucefc downloader.
Home-page: http://code.foxe6.kozow.com/ucefcdownloader/
Author: f̣ộx̣ệ6
Author-email: foxe6@pm.me
License: AGPL-3.0
Project-URL: Sourcecode, http://code.foxe6.kozow.com/ucefcdownloader.zip
Project-URL: Documentation, http://code.foxe6.kozow.com/ucefcdownloader/docs/
Project-URL: Example, http://code.foxe6.kozow.com/ucefcdownloader/test/
Project-URL: Funding, https://paypal.me/foxe6
Project-URL: Say Thanks!, https://saythanks.io/to/foxe6
Keywords: ucefc downloader
Platform: UNKNOWN
Classifier: Programming Language :: Python :: 3.9
Classifier: Topic :: Utilities
Classifier: Natural Language :: English
Classifier: Intended Audience :: Developers
Classifier: License :: OSI Approved :: GNU Affero General Public License v3
Classifier: Operating System :: MacOS
Classifier: Operating System :: POSIX
Classifier: Operating System :: Microsoft :: Windows :: Windows 10
Classifier: Development Status :: 5 - Production/Stable
Requires-Python: >=3.5
